aiofdfs/__init__.py
aiofdfs/async_client.py
aiofdfs/async_connection.py
aiofdfs/async_fastapi_file_handle.py
aiofdfs/async_fdfs_protol.py
aiofdfs/async_storage_client.py
aiofdfs/async_tracker_client.py
aiofdfs/exceptions.py
aiofdfs/fdfs_conf.py
aiofdfs/py.typed
aiofdfs/entity/__init__.py
aiofdfs/entity/group_info.py
aiofdfs/entity/storage_info.py
aiofdfs/util/__init__.py
aiofdfs/util/async_utils.py
aiofdfs-0.1.26.dist-info/METADATA
aiofdfs-0.1.26.dist-info/WHEEL
aiofdfs-0.1.26.dist-info/RECORD
