Metadata-Version: 2.4
Name: aiofdfs
Version: 0.1.26
Summary: A crude but basically usable fastdfs client based on asyncio
Author-email: ferdinand <gongjpa@gmail.com>
License-Expression: Apache-2.0 OR MIT
Keywords: aio,asyncio,client,fastdfs
Classifier: Development Status :: 4 - Beta
Classifier: Intended Audience :: Developers
Classifier: License :: OSI Approved :: Apache Software License
Classifier: License :: OSI Approved :: MIT License
Classifier: Operating System :: OS Independent
Classifier: Programming Language :: Python :: 3
Classifier: Programming Language :: Python :: 3.12
Classifier: Topic :: Software Development :: Libraries :: Python Modules
Requires-Python: >=3.12
Requires-Dist: aiofiles<26,>=24
